net_operations/__init__.py
net_operations/lib/__init__.py
net_operations/lib/cisco/brases_funcs.py
net_operations/lib/classes/NetDevices.py
net_operations/lib/classes/NetFiles.py
net_operations/lib/classes/NetOperations.py
net_operations/lib/classes/NetUser.py
net_operations/lib/constants.py
net_operations/lib/funcs.py
net_operations/lib/huawei/acc_users_funcs.py
net_operations/lib/huawei/main_info_funcs.py
net_operations/lib/huawei/nat_funcs.py
net_operations/lib/logger.py
net_operations/lib/report_templates.py
net_operations/lib/script_funcs.py
net_operations/remarks.md
net_operations/scripts/__init__.py
net_operations/scripts/reports.py
net_operations-202309.1.dist-info/METADATA
net_operations-202309.1.dist-info/WHEEL
net_operations-202309.1.dist-info/entry_points.txt
net_operations-202309.1.dist-info/RECORD
