Metadata-Version: 2.1
Name: net-operations
Version: 202309.1
Summary: 
Author: modemfux
Author-email: modemfux@gmail.com
Requires-Python: >=3.9,<4.0
Classifier: Programming Language :: Python :: 3
Classifier: Programming Language :: Python :: 3.9
Classifier: Programming Language :: Python :: 3.10
Classifier: Programming Language :: Python :: 3.11
Requires-Dist: jinja2 (>=3.1.2,<4.0.0)
Requires-Dist: paramiko (>=3.2.0,<4.0.0)
Requires-Dist: pyyaml (>=6.0,<7.0)
